LICENSE
MANIFEST.in
README.md
VERSION
setup.py
lase/__init__.py
lase/git.py
lase/version.py
laserbeam.egg-info/PKG-INFO
laserbeam.egg-info/SOURCES.txt
laserbeam.egg-info/dependency_links.txt
laserbeam.egg-info/entry_points.txt
laserbeam.egg-info/requires.txt
laserbeam.egg-info/top_level.txt